pnsgraph/MSG.py
pnsgraph/SSG.py
pnsgraph/__init__.py
pnsgraph/pgraph.py
pnsgraph/testfile.py
pnsgraph-0.1.2.dist-info/METADATA
pnsgraph-0.1.2.dist-info/WHEEL
pnsgraph-0.1.2.dist-info/licenses/LICENSE
pnsgraph-0.1.2.dist-info/RECORD
