Metadata-Version: 2.4
Name: pnsgraph
Version: 0.1.2
Summary: Python Implementation of P-graph Algorithms for Process Network Synthesis
Project-URL: Homepage, https://github.com/fredtapia/PNS-Graph
Author-email: John Frederick Tapia <john.frederick.tapia@dlsu.edu.ph>
License: Copyright (c) 2023 John Frederick D. Tapia
License-File: LICENSE
Keywords: network,p-graph,process synthesis
Classifier: Intended Audience :: Developers
Classifier: Operating System :: OS Independent
Classifier: Programming Language :: Python :: 3
Requires-Python: >=3.7
Requires-Dist: pulp
